{
  "matchday": 30,
  "totalPoints": 0,
  "totalBudget": 59590320,
  "timestamp": "2026-04-24T08:24:55.375Z",
  "lineup": [
    {
      "id": "4590",
      "teamId": "7",
      "name": "Jonas Omlin",
      "position": 1,
      "marketValue": 500000,
      "points": 0
    },
    {
      "id": "54",
      "teamId": 3,
      "name": "Can",
      "position": 2,
      "marketValue": 500000,
      "points": 0
    },
    {
      "id": "461",
      "teamId": 4,
      "name": "Chandler",
      "position": 2,
      "marketValue": 500000,
      "points": 0
    },
    {
      "id": "660",
      "teamId": 2,
      "name": "Goretzka",
      "position": 3,
      "marketValue": 23210075,
      "points": 0
    },
    {
      "id": "1192",
      "teamId": 3,
      "name": "Brandt",
      "position": 3,
      "marketValue": 19752212,
      "points": 0
    },
    {
      "id": "4280",
      "teamId": 2,
      "name": "Jackson",
      "position": 4,
      "marketValue": 6938779,
      "points": 0
    },
    {
      "id": "550",
      "teamId": "18",
      "name": "Stefan Bell",
      "position": 1313,
      "marketValue": 866940,
      "points": 0
    },
    {
      "id": "72",
      "teamId": "7",
      "name": "Mark Flekken",
      "position": 1932,
      "marketValue": 7322314,
      "points": 0
    }
  ]
}